<?xml version="1.0" encoding="UTF-8"?>
<metadata xml:lang="es"><Esri><CreaDate>20240506</CreaDate><CreaTime>10495400</CreaTime><ArcGISFormat>1.0</ArcGISFormat><SyncOnce>TRUE</SyncOnce><DataProperties><lineage><Process ToolSource="c:\program files (x86)\arcgis\desktop10.5\ArcToolbox\Toolboxes\Spatial Analyst Tools.tbx\KernelDensity" Date="20240506" Time="104954">KernelDensity C:/Paleospeleology/Accessibility\CostLCP.shp grid_code C:/Paleospeleology/Accessibility\GreaterDifficulties.tif 0,25 2 SQUARE_MAP_UNITS DENSITIES PLANAR</Process></lineage></DataProperties></Esri></metadata>
